{"duration":24,"EndTime":"2020-10-23T11:17:58.620","activities":[{"duration":16,"EndTime":"2020-10-23T11:17:52.619","activities":[{"duration":16,"EndTime":"2020-10-23T11:17:52.619","activities":[{"duration":10,"intervals":[{"duration":10,"EndTime":"2020-10-23T11:17:50.620","StartTime":"2020-10-23T11:17:40.620"}],"EndTime":"2020-10-23T11:17:50.620","name":"first list","StartTime":"2020-10-23T11:17:40.620","active":false,"type":"Task"},{"duration":6,"intervals":[{"duration":6,"EndTime":"2020-10-23T11:17:52.619","StartTime":"2020-10-23T11:17:46.620"}],"EndTime":"2020-10-23T11:17:52.619","name":"second list","StartTime":"2020-10-23T11:17:46.620","active":false,"type":"Task"}],"name":"Problems","StartTime":"2020-10-23T11:17:40.620","type":"Project"},{"duration":0,"EndTime":"null","activities":[{"duration":0,"intervals":[],"EndTime":"null","name":"Read handout","StartTime":"null","active":false,"type":"Task"},{"duration":0,"intervals":[],"EndTime":"null","name":"first milestone","StartTime":"null","active":false,"type":"Task"}],"name":"project time tracker","StartTime":"null","type":"Project"}],"name":"Software design","StartTime":"2020-10-23T11:17:40.620","type":"Project"},{"duration":0,"EndTime":"null","activities":[],"name":"Software testing","StartTime":"null","type":"Project"},{"duration":0,"EndTime":"null","activities":[],"name":"Databases","StartTime":"null","type":"Project"},{"duration":8,"intervals":[{"duration":4,"EndTime":"2020-10-23T11:17:38.620","StartTime":"2020-10-23T11:17:34.619"},{"duration":4,"EndTime":"2020-10-23T11:17:58.620","StartTime":"2020-10-23T11:17:54.621"}],"EndTime":"2020-10-23T11:17:58.620","name":"transportation","StartTime":"2020-10-23T11:17:34.619","active":false,"type":"Task"}],"name":"ROOT_NODE","StartTime":"2020-10-23T11:17:34.619","type":"Project"}